fastprocess/__init__.py
fastprocess/fastprocess.py
fastprocess-2.1.1.dist-info/METADATA
fastprocess-2.1.1.dist-info/WHEEL
fastprocess-2.1.1.dist-info/licenses/LICENSE
fastprocess-2.1.1.dist-info/RECORD
