Metadata-Version: 2.4
Name: fastprocess
Version: 2.1.1
Summary: A fast subprocess library
Project-URL: homepage, https://github.com/dstathis/fastprocess
Project-URL: issues, https://github.com/dstathis/fastprocess/issues
Author-email: Dylan Stephano-Shachter <dylan@theone.ninja>
License-File: LICENSE
Classifier: Development Status :: 4 - Beta
Classifier: License :: OSI Approved :: GNU Lesser General Public License v3 (LGPLv3)
Classifier: Operating System :: POSIX
Classifier: Programming Language :: Python
Classifier: Topic :: Software Development :: Libraries :: Python Modules
Requires-Python: >=3.8
